lightning_boost/cli/__init__.py
lightning_boost/cli/cli.py
lightning_boost/core/__init__.py
lightning_boost/core/callbacks/__init__.py
lightning_boost/core/callbacks/model_summary.py
lightning_boost/data/__init__.py
lightning_boost/data/datamodules/__init__.py
lightning_boost/data/datamodules/base_datamodule.py
lightning_boost/data/datasets/__init__.py
lightning_boost/data/datasets/base_dataset.py
lightning_boost/models/__init__.py
lightning_boost/models/base_model.py
lightning_boost/modules/__init__.py
lightning_boost/modules/loss/__init__.py
lightning_boost/modules/loss/task_loss.py
lightning_boost/modules/metrics/__init__.py
lightning_boost/modules/metrics/task_metric.py
lightning_boost/modules/optim/__init__.py
lightning_boost/modules/optim/lr_scheduling_policy.py
lightning_boost/modules/preprocessing/__init__.py
lightning_boost/modules/preprocessing/base_collator.py
lightning_boost/modules/preprocessing/base_transform.py
lightning_boost/modules/preprocessing/composite_transform.py
lightning_boost/systems/__init__.py
lightning_boost/systems/base_system.py
lightning_boost/systems/utils.py
lightning_boost-2.0.1.dist-info/METADATA
lightning_boost-2.0.1.dist-info/WHEEL
lightning_boost-2.0.1.dist-info/RECORD
