Metadata-Version: 2.1
Name: lightning-boost
Version: 2.0.1
Summary: PyTorch Lightning extension for faster model development.
Home-page: https://github.com/f-lair/lightning-boost
License: Apache-2.0
Author: Fabrice von der Lehr
Author-email: fabrice.vonderlehr222@gmail.com
Requires-Python: >=3.10,<4.0
Classifier: License :: OSI Approved :: Apache Software License
Classifier: Programming Language :: Python :: 3
Classifier: Programming Language :: Python :: 3.10
Classifier: Programming Language :: Python :: 3.11
Requires-Dist: inflection (>=0.5.1,<0.6.0)
Requires-Dist: jsonargparse[signatures] (>=4.24.1,<5.0.0)
Requires-Dist: lightning (>=2.0.8,<3.0.0)
Requires-Dist: tensorboard (>=2.14.0,<3.0.0)
Requires-Dist: torch (>=2.0.1,<3.0.0)
Requires-Dist: torchmetrics (>=1.1.1,<2.0.0)
Requires-Dist: torchvision (>=0.15.2,<0.16.0)
Project-URL: Documentation, https://lightning-boost.readthedocs.io/en/latest/
Project-URL: Repository, https://github.com/f-lair/lightning-boost
